{
  "name": "plan007-notify-migration",
  "description": "ADR-021 — Discord 알림 openclaw 경유 + 워크스페이스 .env 격리. _shared/lib/notify_discord.ts 재구현 (webhook → openclaw subprocess + --media), career-os caller 갱신 (--env-file=<ws>/.env 패턴) + .env.example 신설, run-phases.py find_notify_script 통합. apartment 마이그레이션은 별도 plan (워크스페이스 격리).",
  "created_at": "2026-05-14T01:30:00+00:00",
  "updated_at": "2026-05-14T01:30:00+00:00",
  "status": "pending",
  "current_phase": 1,
  "total_phases": 4,
  "error_message": null,
  "blocked_reason": null,
  "related_docs": [
    "career-os/docs/adr.md",
    "career-os/docs/code-architecture.md",
    "career-os/docs/data-schema.md",
    "career-os/docs/flow.md",
    "career-os/AGENTS.md"
  ],
  "depends_on": [
    "plan006-workspace-scripts-restructure"
  ],
  "phases": [
    {
      "number": 1,
      "title": "_shared/lib/notify_discord.ts 재구현 (openclaw subprocess + --media) + types 갱신 + unit smoke",
      "file": "phase-01.md",
      "status": "pending",
      "allowedTools": ["Read", "Write", "Edit", "Bash", "Grep"],
      "model": "sonnet",
      "timeout": 600
    },
    {
      "number": 2,
      "title": "career-os caller 갱신 (bun --env-file=<ws>/.env 패턴) + career-os/.env.example 신설",
      "file": "phase-02.md",
      "status": "pending",
      "allowedTools": ["Read", "Write", "Edit", "Bash", "Grep"],
      "model": "sonnet",
      "timeout": 900
    },
    {
      "number": 3,
      "title": "skills/plan-and-build/scripts/run-phases.py 갱신 (find_notify_script 폐기 + --env-file)",
      "file": "phase-03.md",
      "status": "pending",
      "allowedTools": ["Read", "Edit", "Bash", "Grep"],
      "model": "sonnet",
      "timeout": 600
    },
    {
      "number": 4,
      "title": "통합 smoke + 잔재 grep + push + trailing cleanup",
      "file": "phase-04.md",
      "status": "pending",
      "allowedTools": ["Read", "Edit", "Bash", "Grep"],
      "model": "sonnet",
      "timeout": 600
    }
  ]
}
